odoo/addons/invader_payment_adyen_klarna_invoice/README.rst
odoo/addons/invader_payment_adyen_klarna_invoice/__init__.py
odoo/addons/invader_payment_adyen_klarna_invoice/__manifest__.py
odoo/addons/invader_payment_adyen_klarna_invoice/i18n/invader_payment_adyen_klarna_invoice.pot
odoo/addons/invader_payment_adyen_klarna_invoice/models/__init__.py
odoo/addons/invader_payment_adyen_klarna_invoice/models/account_move.py
odoo/addons/invader_payment_adyen_klarna_invoice/readme/CONFIGURE.rst
odoo/addons/invader_payment_adyen_klarna_invoice/readme/CONTRIBUTORS.rst
odoo/addons/invader_payment_adyen_klarna_invoice/readme/DESCRIPTION.rst
odoo/addons/invader_payment_adyen_klarna_invoice/readme/HISTORY.rst
odoo/addons/invader_payment_adyen_klarna_invoice/static/description/index.html
odoo14_addon_invader_payment_adyen_klarna_invoice-14.0.1.0.3.dist-info/METADATA
odoo14_addon_invader_payment_adyen_klarna_invoice-14.0.1.0.3.dist-info/WHEEL
odoo14_addon_invader_payment_adyen_klarna_invoice-14.0.1.0.3.dist-info/top_level.txt
odoo14_addon_invader_payment_adyen_klarna_invoice-14.0.1.0.3.dist-info/RECORD
